Workbook

Sheet Irregularidad BCRA
A1: Crédito a empresas
A2: Fecha | B2: Letra CLANAE | C2: Sector | D2: Préstamos totales | E2: Préstamos sit. Normal | F2: Irregularidad (%)
A3: 43921 | B3: A | C3: Agro | D3: 280583840 | E3: 262359525 | F3: 6.4951406
A4: 44012 | B4: A | C4: Agro | D4: 329181858 | E4: 311378236 | F4: 5.4084457
A5: 44104 | B5: A | C5: Agro | D5: 360172298 | E5: 340772195 | F5: 5.3863396
A6: 44196 | B6: A | C6: Agro | D6: 420635037 | E6: 400822867 | F6: 4.7100618
A7: 44286 | B7: A | C7: Agro | D7: 408064939 | E7: 386435819 | F7: 5.3004113
A8: 44377 | B8: A | C8: Agro | D8: 437089786 | E8: 410910846 | F8: 5.9893735
A9: 44469 | B9: A | C9: Agro | D9: 465605151 | E9: 438097111 | F9: 5.9080188
A10: 44561 | B10: A | C10: Agro | D10: 570294057 | E10: 539065176 | F10: 5.4759261
A11: 44651 | B11: A | C11: Agro | D11: 628453156 | E11: 603355795 | F11: 3.9935134
A12: 44742 | B12: A | C12: Agro | D12: 757560760 | E12: 734475166 | F12: 3.0473587
A13: 44834 | B13: A | C13: Agro | D13: 843899366 | E13: 818792752 | F13: 2.975072
A14: 44926 | B14: A | C14: Agro | D14: 917062153 | E14: 886823976 | F14: 3.2972876
... A314: 46022 | B314: M+N | C314: Educ./Salud | D314: 1478807956 | E314: 1359830145 | F314: 8.0455214

Sheet Irregularidad agregada
A1: Irregularidad agregada para sectores
A2: Fecha | B2: Total (excl. L) | C2: Normal (excl. L) | D2: Irreg. ponderada excl. L (%) | E2: Total (todos) | F2: Normal (todos) | G2: Irreg. ponderada todos (%)
A3: 43921 | B3: =SUMIFS('Irregularidad BCRA'!$D$3:$D$314,'Irregularidad BCRA'!$A$3:$A$314,A3,'Irregularidad BCRA'!$B$3:$B$314,"<>L") -> 1463047338 | C3: =SUMIFS('Irregularidad BCRA'!$E$3:$E$314,'Irregularidad BCRA'!$A$3:$A$314,A3,'Irregularidad BCRA'!$B$3:$B$314,"<>L") -> 1338513185 | D3: =(B3-C3)/B3*100 -> 8.5119702 | E3: =SUMIF('Irregularidad BCRA'!$A$3:$A$314,A3,'Irregularidad BCRA'!$D$3:$D$314) -> 1540149080 | F3: =SUMIF('Irregularidad BCRA'!$A$3:$A$314,A3,'Irregularidad BCRA'!$E$3:$E$314) -> 1415511473 | G3: =(E3-F3)/E3*100 -> 8.0925677
A4: 44012 | B4: =SUMIFS('Irregularidad BCRA'!$D$3:$D$314,'Irregularidad BCRA'!$A$3:$A$314,A4,'Irregularidad BCRA'!$B$3:$B$314,"<>L") -> 1643704212 | C4: =SUMIFS('Irregularidad BCRA'!$E$3:$E$314,'Irregularidad BCRA'!$A$3:$A$314,A4,'Irregularidad BCRA'!$B$3:$B$314,"<>L") -> 1517432417 | D4: =(B4-C4)/B4*100 -> 7.6821483 | E4: =SUMIF('Irregularidad BCRA'!$A$3:$A$314,A4,'Irregularidad BCRA'!$D$3:$D$314) -> 1698940985 | F4: =SUMIF('Irregularidad BCRA'!$A$3:$A$314,A4,'Irregularidad BCRA'!$E$3:$E$314) -> 1572641042 | G4: =(E4-F4)/E4*100 -> 7.4340394
A5: 44104 | B5: =SUMIFS('Irregularidad BCRA'!$D$3:$D$314,'Irregularidad BCRA'!$A$3:$A$314,A5,'Irregularidad BCRA'!$B$3:$B$314,"<>L") -> 1695994791 | C5: =SUMIFS('Irregularidad BCRA'!$E$3:$E$314,'Irregularidad BCRA'!$A$3:$A$314,A5,'Irregularidad BCRA'!$B$3:$B$314,"<>L") -> 1572094460 | D5: =(B5-C5)/B5*100 -> 7.3054665 | E5: =SUMIF('Irregularidad BCRA'!$A$3:$A$314,A5,'Irregularidad BCRA'!$D$3:$D$314) -> 1747050254 | F5: =SUMIF('Irregularidad BCRA'!$A$3:$A$314,A5,'Irregularidad BCRA'!$E$3:$E$314) -> 1623127732 | G5: =(E5-F5)/E5*100 -> 7.0932431
A6: 44196 | B6: =SUMIFS('Irregularidad BCRA'!$D$3:$D$314,'Irregularidad BCRA'!$A$3:$A$314,A6,'Irregularidad BCRA'!$B$3:$B$314,"<>L") -> 1873577885 | C6: =SUMIFS('Irregularidad BCRA'!$E$3:$E$314,'Irregularidad BCRA'!$A$3:$A$314,A6,'Irregularidad BCRA'!$B$3:$B$314,"<>L") -> 1743213099 | D6: =(B6-C6)/B6*100 -> 6.958066 | E6: =SUMIF('Irregularidad BCRA'!$A$3:$A$314,A6,'Irregularidad BCRA'!$D$3:$D$314) -> 1940034928 | F6: =SUMIF('Irregularidad BCRA'!$A$3:$A$314,A6,'Irregularidad BCRA'!$E$3:$E$314) -> 1809660143 | G6: =(E6-F6)/E6*100 -> 6.7202288
A7: 44286 | B7: =SUMIFS('Irregularidad BCRA'!$D$3:$D$314,'Irregularidad BCRA'!$A$3:$A$314,A7,'Irregularidad BCRA'!$B$3:$B$314,"<>L") -> 1910766785 | C7: =SUMIFS('Irregularidad BCRA'!$E$3:$E$314,'Irregularidad BCRA'!$A$3:$A$314,A7,'Irregularidad BCRA'!$B$3:$B$314,"<>L") -> 1773036838 | D7: =(B7-C7)/B7*100 -> 7.2080982 | E7: =SUMIF('Irregularidad BCRA'!$A$3:$A$314,A7,'Irregularidad BCRA'!$D$3:$D$314) -> 1971481577 | F7: =SUMIF('Irregularidad BCRA'!$A$3:$A$314,A7,'Irregularidad BCRA'!$E$3:$E$314) -> 1833069057 | G7: =(E7-F7)/E7*100 -> 7.0207362
A8: 44377 | B8: =SUMIFS('Irregularidad BCRA'!$D$3:$D$314,'Irregularidad BCRA'!$A$3:$A$314,A8,'Irregularidad BCRA'!$B$3:$B$314,"<>L") -> 2030815627 | C8: =SUMIFS('Irregularidad BCRA'!$E$3:$E$314,'Irregularidad BCRA'!$A$3:$A$314,A8,'Irregularidad BCRA'!$B$3:$B$314,"<>L") -> 1869909919 | D8: =(B8-C8)/B8*100 -> 7.9232061 | E8: =SUMIF('Irregularidad BCRA'!$A$3:$A$314,A8,'Irregularidad BCRA'!$D$3:$D$314) -> 2103923554 | F8: =SUMIF('Irregularidad BCRA'!$A$3:$A$314,A8,'Irregularidad BCRA'!$E$3:$E$314) -> 1942995471 | G8: =(E8-F8)/E8*100 -> 7.6489511
A9: 44469 | B9: =SUMIFS('Irregularidad BCRA'!$D$3:$D$314,'Irregularidad BCRA'!$A$3:$A$314,A9,'Irregularidad BCRA'!$B$3:$B$314,"<>L") -> 2228679341 | C9: =SUMIFS('Irregularidad BCRA'!$E$3:$E$314,'Irregularidad BCRA'!$A$3:$A$314,A9,'Irregularidad BCRA'!$B$3:$B$314,"<>L") -> 2068695596 | D9: =(B9-C9)/B9*100 -> 7.1784102 | E9: =SUMIF('Irregularidad BCRA'!$A$3:$A$314,A9,'Irregularidad BCRA'!$D$3:$D$314) -> 2297544003 | F9: =SUMIF('Irregularidad BCRA'!$A$3:$A$314,A9,'Irregularidad BCRA'!$E$3:$E$314) -> 2137504953 | G9: =(E9-F9)/E9*100 -> 6.9656577
A10: 44561 | B10: =SUMIFS('Irregularidad BCRA'!$D$3:$D$314,'Irregularidad BCRA'!$A$3:$A$314,A10,'Irregularidad BCRA'!$B$3:$B$314,"<>L") -> 2631563554 | C10: =SUMIFS('Irregularidad BCRA'!$E$3:$E$314,'Irregularidad BCRA'!$A$3:$A$314,A10,'Irregularidad BCRA'!$B$3:$B$314,"<>L") -> 2451091727 | D10: =(B10-C10)/B10*100 -> 6.8579695 | E10: =SUMIF('Irregularidad BCRA'!$A$3:$A$314,A10,'Irregularidad BCRA'!$D$3:$D$314) -> 2708677605 | F10: =SUMIF('Irregularidad BCRA'!$A$3:$A$314,A10,'Irregularidad BCRA'!$E$3:$E$314) -> 2528115665 | G10: =(E10-F10)/E10*100 -> 6.666055
A11: 44651 | B11: =SUMIFS('Irregularidad BCRA'!$D$3:$D$314,'Irregularidad BCRA'!$A$3:$A$314,A11,'Irregularidad BCRA'!$B$3:$B$314,"<>L") -> 2857745919 | C11: =SUMIFS('Irregularidad BCRA'!$E$3:$E$314,'Irregularidad BCRA'!$A$3:$A$314,A11,'Irregularidad BCRA'!$B$3:$B$314,"<>L") -> 2678642361 | D11: =(B11-C11)/B11*100 -> 6.2673017 | E11: =SUMIF('Irregularidad BCRA'!$A$3:$A$314,A11,'Irregularidad BCRA'!$D$3:$D$314) -> 2940589887 | F11: =SUMIF('Irregularidad BCRA'!$A$3:$A$314,A11,'Irregularidad BCRA'!$E$3:$E$314) -> 2761434942 | G11: =(E11-F11)/E11*100 -> 6.0924832
A12: 44742 | B12: =SUMIFS('Irregularidad BCRA'!$D$3:$D$314,'Irregularidad BCRA'!$A$3:$A$314,A12,'Irregularidad BCRA'!$B$3:$B$314,"<>L") -> 3452439657 | C12: =SUMIFS('Irregularidad BCRA'!$E$3:$E$314,'Irregularidad BCRA'!$A$3:$A$314,A12,'Irregularidad BCRA'!$B$3:$B$314,"<>L") -> 3277113004 | D12: =(B12-C12)/B12*100 -> 5.0783408 | E12: =SUMIF('Irregularidad BCRA'!$A$3:$A$314,A12,'Irregularidad BCRA'!$D$3:$D$314) -> 3550934798 | F12: =SUMIF('Irregularidad BCRA'!$A$3:$A$314,A12,'Irregularidad BCRA'!$E$3:$E$314) -> 3375562818 | G12: =(E12-F12)/E12*100 -> 4.9387553
A13: 44834 | B13: =SUMIFS('Irregularidad BCRA'!$D$3:$D$314,'Irregularidad BCRA'!$A$3:$A$314,A13,'Irregularidad BCRA'!$B$3:$B$314,"<>L") -> 3790530157 | C13: =SUMIFS('Irregularidad BCRA'!$E$3:$E$314,'Irregularidad BCRA'!$A$3:$A$314,A13,'Irregularidad BCRA'!$B$3:$B$314,"<>L") -> 3592124212 | D13: =(B13-C13)/B13*100 -> 5.2342532 | E13: =SUMIF('Irregularidad BCRA'!$A$3:$A$314,A13,'Irregularidad BCRA'!$D$3:$D$314) -> 3894785002 | F13: =SUMIF('Irregularidad BCRA'!$A$3:$A$314,A13,'Irregularidad BCRA'!$E$3:$E$314) -> 3696338823 | G13: =(E13-F13)/E13*100 -> 5.0951767
A14: 44926 | B14: =SUMIFS('Irregularidad BCRA'!$D$3:$D$314,'Irregularidad BCRA'!$A$3:$A$314,A14,'Irregularidad BCRA'!$B$3:$B$314,"<>L") -> 4355694739 | C14: =SUMIFS('Irregularidad BCRA'!$E$3:$E$314,'Irregularidad BCRA'!$A$3:$A$314,A14,'Irregularidad BCRA'!$B$3:$B$314,"<>L") -> 4129316398 | D14: =(B14-C14)/B14*100 -> 5.1972958 | E14: =SUMIF('Irregularidad BCRA'!$A$3:$A$314,A14,'Irregularidad BCRA'!$D$3:$D$314) -> 4480672596 | F14: =SUMIF('Irregularidad BCRA'!$A$3:$A$314,A14,'Irregularidad BCRA'!$E$3:$E$314) -> 4254075134 | G14: =(E14-F14)/E14*100 -> 5.0572198
... A26: 46022 | B26: =SUMIFS('Irregularidad BCRA'!$D$3:$D$314,'Irregularidad BCRA'!$A$3:$A$314,A26,'Irregularidad BCRA'!$B$3:$B$314,"<>L") -> 74624370438 | C26: =SUMIFS('Irregularidad BCRA'!$E$3:$E$314,'Irregularidad BCRA'!$A$3:$A$314,A26,'Irregularidad BCRA'!$B$3:$B$314,"<>L") -> 71199272617 | D26: =(B26-C26)/B26*100 -> 4.5897845 | E26: =SUMIF('Irregularidad BCRA'!$A$3:$A$314,A26,'Irregularidad BCRA'!$D$3:$D$314) -> 76016852734 | F26: =SUMIF('Irregularidad BCRA'!$A$3:$A$314,A26,'Irregularidad BCRA'!$E$3:$E$314) -> 72513539219 | G26: =(E26-F26)/E26*100 -> 4.6086011

Sheet EMAE
A1: Fecha | B1: Año | C1: Mes | D1: A | E1: B | F1: C | G1: D | H1: E | I1: F | J1: G | K1: H | L1: I | M1: J | N1: K | O1: L | P1: M | Q1: N | R1: M+N
A2: 43831 | B2: 2020 | C2: 1 | D2: 84.7799 | E2: 101.70896 | F2: 88.023249 | G2: 101.71477 | H2: 151.9216 | I2: 129.90481 | J2: 129.37967 | K2: 176.60007 | L2: 182.93542 | M2: 161.53151 | N2: 137.10218 | O2: 155.78383 | P2: 157.66668 | Q2: 181.05884 | R2: 169.36276
A3: 43862 | B3: 2020 | C3: 2 | D3: 68.525431 | E3: 183.55052 | F3: 85.928472 | G3: 102.30741 | H3: 140.2243 | I3: 125.26752 | J3: 129.57229 | K3: 170.13846 | L3: 177.4565 | M3: 154.45575 | N3: 136.28604 | O3: 156.31203 | P3: 158.40507 | Q3: 172.60279 | R3: 165.50393
A4: 43891 | B4: 2020 | C4: 3 | D4: 138.79893 | E4: 80.919238 | F4: 85.812133 | G4: 98.96455 | H4: 146.29745 | I4: 97.69679 | J4: 126.98197 | K4: 102.43045 | L4: 163.95509 | M4: 171.18756 | N4: 129.57605 | O4: 154.35988 | P4: 158.28215 | Q4: 169.01531 | R4: 163.64873
A5: 43922 | B5: 2020 | C5: 4 | D5: 210.48257 | E5: 128.83597 | F5: 69.766034 | G5: 78.015611 | H5: 119.98719 | I5: 43.886063 | J5: 106.49372 | K5: 24.08034 | L5: 143.87525 | M5: 165.46846 | N5: 116.111 | O5: 135.06847 | P5: 145.01253 | Q5: 125.10485 | R5: 135.05869
A6: 43952 | B6: 2020 | C6: 5 | D6: 294.48952 | E6: 153.34525 | F6: 74.910883 | G6: 93.104996 | H6: 132.75669 | I6: 75.02261 | J6: 118.0885 | K6: 42.754245 | L6: 162.27754 | M6: 155.63397 | N6: 122.70226 | O6: 136.45071 | P6: 149.29121 | Q6: 154.79297 | R6: 152.04209
A7: 43983 | B7: 2020 | C7: 6 | D7: 200.89476 | E7: 88.79622 | F7: 75.17548 | G7: 113.41104 | H7: 143.29377 | I7: 95.340611 | J7: 133.52314 | K7: 58.57499 | L7: 158.98517 | M7: 166.86491 | N7: 128.61073 | O7: 137.29755 | P7: 149.84682 | Q7: 163.00889 | R7: 156.42786
A8: 44013 | B8: 2020 | C8: 7 | D8: 117.04971 | E8: 86.84341 | F8: 78.698087 | G8: 114.60883 | H8: 158.8599 | I8: 114.83527 | J8: 136.16197 | K8: 58.855169 | L8: 150.62536 | M8: 166.52923 | N8: 130.24777 | O8: 141.06344 | P8: 153.45983 | Q8: 164.44575 | R8: 158.95279
A9: 44044 | B9: 2020 | C9: 8 | D9: 75.823748 | E9: 264.27941 | F9: 80.995709 | G9: 114.39875 | H9: 144.581 | I9: 117.71328 | J9: 134.44212 | K9: 71.335315 | L9: 149.94997 | M9: 171.17913 | N9: 134.64434 | O9: 140.02553 | P9: 153.09201 | Q9: 162.48296 | R9: 157.78748
A10: 44075 | B10: 2020 | C10: 9 | D10: 73.787097 | E10: 237.46872 | F10: 77.025752 | G10: 119.25292 | H10: 133.95363 | I10: 116.46579 | J10: 141.8424 | K10: 63.822216 | L10: 152.13612 | M10: 167.26529 | N10: 135.8179 | O10: 140.58376 | P10: 155.10667 | Q10: 166.23307 | R10: 160.66987
A11: 44105 | B11: 2020 | C11: 10 | D11: 73.327101 | E11: 162.64909 | F11: 79.675167 | G11: 127.43489 | H11: 132.34636 | I11: 133.11965 | J11: 145.26537 | K11: 75.241091 | L11: 151.68675 | M11: 172.65112 | N11: 137.68023 | O11: 143.15187 | P11: 156.54106 | Q11: 169.6862 | R11: 163.11363
A12: 44136 | B12: 2020 | C12: 11 | D12: 86.966274 | E12: 86.643434 | F12: 76.553093 | G12: 124.64921 | H12: 139.37381 | I12: 137.34945 | J12: 144.4852 | K12: 77.984331 | L12: 153.16144 | M12: 169.18795 | N12: 139.68284 | O12: 143.3086 | P12: 156.78658 | Q12: 169.72033 | R12: 163.25345
A13: 44166 | B13: 2020 | C13: 12 | D13: 112.25613 | E13: 103.05339 | F13: 80.7837 | G13: 118.55058 | H13: 149.97531 | I13: 136.60752 | J13: 144.66512 | K13: 90.324138 | L13: 150.69677 | M13: 175.95488 | N13: 142.27007 | O13: 144.27704 | P13: 157.87222 | Q13: 163.65352 | R13: 160.76287
... A74: 46023 | B74: 2026 | C74: 1 | D74: 114.81245 | E74: 225.57484 | F74: 134.22587 | G74: 104.13722 | H74: 161.76902 | I74: 134.84846 | J74: 142.81135 | K74: 190.50975 | L74: 186.72549 | M74: 197.51828 | N74: 154.30526 | O74: 161.39154 | P74: 168.86084 | Q74: 188.47343 | R74: 178.66713

Sheet Crédito total-PIB
A1: Fecha | B1: Crédito al sector privado (por entidades financieras) prom. trim. (M ARS) | C1: PIB trim. anualizado (M ARS) | D1: Crédito/PIB (%)
A2: 41640 | B2: 506026.12 | C2: 3917648.9 | D2: 12.916577
A3: 41730 | B3: 516163.97 | C3: 4702629.5 | D3: 10.976071
A4: 41821 | B4: 536614.3 | C4: 4685503.1 | D4: 11.452651
A5: 41913 | B5: 569860.37 | C5: 5010564.2 | D5: 11.373178
A6: 42005 | B6: 604285.88 | C6: 5092693.7 | D6: 11.865742
A7: 42095 | B7: 644589.28 | C7: 5951478.9 | D7: 10.830741
A8: 42186 | B8: 696631.27 | C8: 6221730.8 | D8: 11.196744
A9: 42278 | B9: 767089.37 | C9: 6552140.2 | D9: 11.707463
A10: 42370 | B10: 816617.23 | C10: 7006645 | D10: 11.654897
A11: 42461 | B11: 854332.45 | C11: 8414556.5 | D11: 10.15303
A12: 42552 | B12: 914140.78 | C12: 8527628.8 | D12: 10.719753
A13: 42644 | B13: 1000715.5 | C13: 8963807.9 | D13: 11.163955
... A49: 45931 | B49: 1.1194345e+08 | C49: 9.394502e+08 | D49: 11.915847

Sheet Crédito total real
A1: Fecha | B1: Crédito nominal (M ARS) | C1: CER promedio mensual | D1: Crédito real (M ARS, pesos Apr 2026)
A2: 41640 | B2: 500729 | C2: 7.2009091 | D2: 97496943
A3: 41671 | B3: 509333.35 | C3: 7.948 | D3: 89850363
A4: 41699 | B4: 508825.67 | C4: 8.0033333 | D4: 89140217
A5: 41730 | B5: 510124.63 | C5: 8.0773684 | D5: 88548658
A6: 41760 | B6: 515993.95 | C6: 8.1095 | D6: 89212583
A7: 41791 | B7: 522071.35 | C7: 8.192 | D7: 89354309
A8: 41821 | B8: 527621.14 | C8: 8.2209091 | D8: 89986616
A9: 41852 | B9: 537182.65 | C9: 8.3765 | D9: 89915583
A10: 41883 | B10: 545090.77 | C10: 8.4918182 | D10: 90000252
A11: 41913 | B11: 560236.95 | C11: 8.5445455 | D11: 91930235
A12: 41944 | B12: 568496.56 | C12: 8.5766667 | D12: 92936195
A13: 41974 | B13: 582295.32 | C13: 8.6026316 | D13: 94904664
... A147: 46113 | B147: 124126601 | C147: 1402.089 | D147: 124126601

Sheet Definiciones
A1: Concepto | B1: Definición
A2: Irregularidad (proxy) | B2: Irregularidad = (Préstamos totales − Préstamos en situación normal) / Préstamos totales x 100. Incluye situaciones 2 a 6 del BCRA. La definición oficial del BCRA (Informe sobre Bancos) usa sit. 3 a 6 solamente; nuestra medida es más amplia pero consistente para comparación entre sectores.
A3: Sectores | B3: Clasificación Nacional de Actividades Económicas. Match entre BCRA e INDEC (consta de 16 sectores). 13 sectores en los datos BCRA (Se promedian M+N para la variable de actividad), de los cuales usamos 12 (excluimos Administración Pública).
A4: EMAE | B4: Estimador Mensual de Actividad Económica. Índice de volumen físico base 2004=100, calculado por INDEC.
A5: Variación interanual (YoY) | B5: Comparación del mismo trimestre contra el año anterior. Para EMAE (prom cuatrimestral): (EMAE_t / EMAE_{t-4} − 1) × 100. Para irregularidad: diferencia en pp (Irreg_t − Irreg_{t-4}).
A6: Crédito al sector privado | B6: Préstamos de efectivo, en moneda nacional y extranjera, otorgados por las entidades financieras (reguladas por Ley 21.526) al sector privado no financiero residente en el país. Saldos diarios en millones de ARS nominales. No incluye financiamiento vía mercado de capitales (ONs, fideicomisos financieros, leasing extrabancario, etc.). Fuente metodológica: https://www.bcra.gob.ar/principales-variables-datos/?serie=392
A7: CER (deflactor) | B7: Coeficiente de Estabilización de Referencia. Coeficiente diario calculado por el BCRA que sigue la variación del IPC. Se usa para deflactar series nominales. Ventaja vs IPC directo: es una serie continua sin quiebres de base.
A8: Crédito real | B8: Crédito nominal deflactado por CER. Fórmula: Crédito_real = Crédito_nominal / CER_mes x CER_base, donde CER_base es el valor del último mes disponible. Resultado en pesos constantes del último mes.
A9: Crédito / PIB | B9: Stock promedio trimestral de crédito / PIB trimestral a precios corrientes. El PIB de datos.gob.ar viene anualizado (SAAR), por lo que se usa directamente como denominador sin sumar 4 trimestres.
A10: Período de baja inclusión | B10: Q2 2021 a Q3 2023. Crédito/PIB estable en torno a 6-7%. Cartera concentrada en tomadores establecidos.
A11: Período de transición | B11: Q4 2023 a Q2 2024. Cambio de gobierno y fuerte inestabilidad macro. Excluido del análisis econométrico.
A12: Período de alta inclusión | B12: Desde Q3 2024. Crédito/PIB cambia su tendencia. Entrada masiva de nuevos tomadores al sistema y recomposición en la cafrtera de crédito de los bancos.

Sheet Fuentes
A1: Variable | B1: Fuente | C1: Descripción | D1: URL exacta | E1: Frecuencia | F1: Unidad
A2: Préstamos por actividad | B2: BCRA – Boletín Estadístico | C2: Saldos de préstamos por sector, total y situación normal. | D2: https://www.bcra.gob.ar/Pdfs/PublicacionesEstadisticas/act2025.xls | E2: Trimestral | F2: Miles de pesos
A3: EMAE por sector | B3: INDEC | C3: Estimador Mensual de Actividad Económica por letra sector | D3: https://www.indec.gob.ar/ftp/cuadros/economia/sh_emae_actividad_base2004.xls | E3: Mensual | F3: Índice base 2004=100
A4: EMAE general | B4: INDEC | C4: EMAE serie general mensual. | D4: https://www.indec.gob.ar/ftp/cuadros/economia/sh_emae_mensual_base2004.xls | E4: Mensual | F4: Índice base 2004=100
A5: PIB a precios corrientes | B5: INDEC – Cuentas Nacionales (vía datos.gob.ar) | C5: PIB a precios de mercado, precios corrientes. Valores trimestrales anualizados. | D5: https://apis.datos.gob.ar/series/api/series/?ids=11.3_VMATC_2004_T_17&format=csv | E5: Trimestral | F5: Millones de pesos corrientes (anualizado)
A6: Crédito al sector privado | B6: BCRA – API de Estadísticas, Informe Monetario Diario | C6: Préstamos de las entidades financieras al sector privado, saldos diarios. | D6: https://api.bcra.gob.ar/estadisticas/v4.0/Monetarias/26?desde=2014-01-01&hasta=2026-04-30 | E6: Diaria | F6: Millones de pesos
A7: CER | B7: BCRA – API de Estadísticas | C7: Coeficiente de Estabilización de Referencia. Se construye a partir del IPC; sirve como deflactor continuo sin quiebres de base. | D7: https://api.bcra.gob.ar/estadisticas/v4.0/Monetarias/4?desde=2014-01-01&hasta=2026-04-30 | E7: Diaria | F7: Coeficiente (base feb 2002=1)
A8: Mora agregada del sistema | B8: BCRA – Series monetarias | C8: % de financiaciones al sector privado en situación normal. | D8: https://www.bcra.gob.ar/Pdfs/PublicacionesEstadisticas/din1_ser.txt | E8: Mensual | F8: Porcentaje
